blue_geo/README.py
blue_geo/__init__.py
blue_geo/__main__.py
blue_geo/config.env
blue_geo/env.py
blue_geo/functions.py
blue_geo/host.py
blue_geo/notebooks.py
blue_geo/sample.env
blue_geo/urls.py
blue_geo/.abcli/QGIS.sh
blue_geo/.abcli/abcli.sh
blue_geo/.abcli/actions.sh
blue_geo/.abcli/aka.sh
blue_geo/.abcli/alias.sh
blue_geo/.abcli/blue_geo.sh
blue_geo/.abcli/catalog.sh
blue_geo/.abcli/datacube.sh
blue_geo/.abcli/gdal.sh
blue_geo/.abcli/ingest.sh
blue_geo/.abcli/install.sh
blue_geo/.abcli/logging.sh
blue_geo/.abcli/watch.sh
blue_geo/.abcli/QGIS/download.sh
blue_geo/.abcli/QGIS/expressions.sh
blue_geo/.abcli/QGIS/server.sh
blue_geo/.abcli/QGIS/templates.sh
blue_geo/.abcli/QGIS/upload.sh
blue_geo/.abcli/catalog/browse.sh
blue_geo/.abcli/catalog/get.sh
blue_geo/.abcli/catalog/list.sh
blue_geo/.abcli/catalog/query.sh
blue_geo/.abcli/catalog/query/ingest.sh
blue_geo/.abcli/catalog/query/label.sh
blue_geo/.abcli/catalog/query/read.sh
blue_geo/.abcli/datacube/crop.sh
blue_geo/.abcli/datacube/generate.sh
blue_geo/.abcli/datacube/get.sh
blue_geo/.abcli/datacube/ingest.sh
blue_geo/.abcli/datacube/label.sh
blue_geo/.abcli/datacube/list.sh
blue_geo/.abcli/gdal/get_crs.sh
blue_geo/.abcli/gdal/install.sh
blue_geo/.abcli/gdal/version.sh
blue_geo/.abcli/tests/README.sh
blue_geo/.abcli/tests/catalog_browse.sh
blue_geo/.abcli/tests/catalog_list.sh
blue_geo/.abcli/tests/catalog_query.sh
blue_geo/.abcli/tests/catalog_query_ingest.sh
blue_geo/.abcli/tests/datacube_crop.sh
blue_geo/.abcli/tests/datacube_generate.sh
blue_geo/.abcli/tests/datacube_get.sh
blue_geo/.abcli/tests/datacube_label.sh
blue_geo/.abcli/tests/datacube_list.sh
blue_geo/.abcli/tests/gdal_get_crs.sh
blue_geo/.abcli/tests/help.sh
blue_geo/.abcli/tests/ingest.sh
blue_geo/.abcli/tests/logging.sh
blue_geo/.abcli/tests/version.sh
blue_geo/.abcli/tests/watch.sh
blue_geo/.abcli/tests/watch_query.sh
blue_geo/.abcli/tests/watch_targets.sh
blue_geo/.abcli/tests/watch_targets_cp.sh
blue_geo/.abcli/tests/watch_targets_get.sh
blue_geo-4.1082.1.dist-info/LICENSE
blue_geo-4.1082.1.dist-info/METADATA
blue_geo-4.1082.1.dist-info/WHEEL
blue_geo-4.1082.1.dist-info/top_level.txt
blue_geo-4.1082.1.dist-info/RECORD
