Metadata-Version: 2.2
Name: blue_geo
Version: 4.1082.1
Summary: 🌐 AI for a Blue Planet.
Home-page: https://github.com/kamangir/blue-geo
Author: Arash Abadpour (Kamangir)
Author-email: arash@kamangir.net
License: Public Domain
Classifier: Programming Language :: Python :: 3
Classifier: Programming Language :: Unix Shell
Classifier: License :: Public Domain
Classifier: Operating System :: OS Independent
License-File: LICENSE
Requires-Dist: abcli
Requires-Dist: blueflow
Requires-Dist: opencv-python
Requires-Dist: shapely!=2.0.7
Requires-Dist: folium
Requires-Dist: geojson
Requires-Dist: geopandas
Requires-Dist: rasterio
Requires-Dist: pystac-client
Dynamic: author
Dynamic: author-email
Dynamic: classifier
Dynamic: description
Dynamic: description-content-type
Dynamic: home-page
Dynamic: license
Dynamic: requires-dist
Dynamic: summary
